{"frames":{"theme_stacked_loop_00000.png":{"frame":{"x":2,"y":572,"w":136,"h":280},"rotated":false,"trimmed":true,"spriteSourceSize":{"x":8,"y":33,"w":136,"h":280},"sourceSize":{"w":150,"h":348}},"theme_stacked_loop_00002.png":{"frame":{"x":142,"y":2,"w":136,"h":280},"rotated":false,"trimmed":true,"spriteSourceSize":{"x":8,"y":33,"w":136,"h":280},"sourceSize":{"w":150,"h":348}},"theme_stacked_loop_00004.png":{"frame":{"x":142,"y":286,"w":136,"h":280},"rotated":false,"trimmed":true,"spriteSourceSize":{"x":8,"y":33,"w":136,"h":280},"sourceSize":{"w":150,"h":348}},"theme_stacked_loop_00006.png":{"frame":{"x":562,"y":286,"w":136,"h":279},"rotated":false,"trimmed":true,"spriteSourceSize":{"x":8,"y":33,"w":136,"h":279},"sourceSize":{"w":150,"h":348}},"theme_stacked_loop_00008.png":{"frame":{"x":562,"y":569,"w":136,"h":279},"rotated":false,"trimmed":true,"spriteSourceSize":{"x":8,"y":33,"w":136,"h":279},"sourceSize":{"w":150,"h":348}},"theme_stacked_loop_00010.png":{"frame":{"x":702,"y":286,"w":136,"h":279},"rotated":false,"trimmed":true,"spriteSourceSize":{"x":8,"y":33,"w":136,"h":279},"sourceSize":{"w":150,"h":348}},"theme_stacked_loop_00012.png":{"frame":{"x":142,"y":570,"w":136,"h":280},"rotated":false,"trimmed":true,"spriteSourceSize":{"x":8,"y":33,"w":136,"h":280},"sourceSize":{"w":150,"h":348}},"theme_stacked_loop_00014.png":{"frame":{"x":282,"y":2,"w":136,"h":280},"rotated":false,"trimmed":true,"spriteSourceSize":{"x":8,"y":33,"w":136,"h":280},"sourceSize":{"w":150,"h":348}},"theme_stacked_loop_00016.png":{"frame":{"x":282,"y":286,"w":136,"h":280},"rotated":false,"trimmed":true,"spriteSourceSize":{"x":8,"y":33,"w":136,"h":280},"sourceSize":{"w":150,"h":348}},"theme_stacked_loop_00018.png":{"frame":{"x":282,"y":570,"w":136,"h":280},"rotated":false,"trimmed":true,"spriteSourceSize":{"x":8,"y":33,"w":136,"h":280},"sourceSize":{"w":150,"h":348}},"theme_stacked_loop_00020.png":{"frame":{"x":422,"y":2,"w":136,"h":280},"rotated":false,"trimmed":true,"spriteSourceSize":{"x":8,"y":33,"w":136,"h":280},"sourceSize":{"w":150,"h":348}},"theme_stacked_loop_00022.png":{"frame":{"x":562,"y":2,"w":136,"h":280},"rotated":false,"trimmed":true,"spriteSourceSize":{"x":8,"y":33,"w":136,"h":280},"sourceSize":{"w":150,"h":348}},"theme_stacked_loop_00024.png":{"frame":{"x":702,"y":2,"w":136,"h":280},"rotated":false,"trimmed":true,"spriteSourceSize":{"x":8,"y":33,"w":136,"h":280},"sourceSize":{"w":150,"h":348}},"theme_stacked_loop_00026.png":{"frame":{"x":842,"y":2,"w":136,"h":280},"rotated":false,"trimmed":true,"spriteSourceSize":{"x":8,"y":33,"w":136,"h":280},"sourceSize":{"w":150,"h":348}},"theme_stacked_loop_00028.png":{"frame":{"x":842,"y":286,"w":136,"h":279},"rotated":false,"trimmed":true,"spriteSourceSize":{"x":8,"y":33,"w":136,"h":279},"sourceSize":{"w":150,"h":348}},"theme_stacked_loop_00030.png":{"frame":{"x":702,"y":569,"w":136,"h":279},"rotated":false,"trimmed":true,"spriteSourceSize":{"x":8,"y":33,"w":136,"h":279},"sourceSize":{"w":150,"h":348}},"theme_stacked_loop_00032.png":{"frame":{"x":422,"y":286,"w":136,"h":280},"rotated":false,"trimmed":true,"spriteSourceSize":{"x":8,"y":33,"w":136,"h":280},"sourceSize":{"w":150,"h":348}},"theme_stacked_loop_00034.png":{"frame":{"x":2,"y":2,"w":136,"h":281},"rotated":false,"trimmed":true,"spriteSourceSize":{"x":8,"y":33,"w":136,"h":281},"sourceSize":{"w":150,"h":348}},"theme_stacked_loop_00036.png":{"frame":{"x":2,"y":287,"w":136,"h":281},"rotated":false,"trimmed":true,"spriteSourceSize":{"x":8,"y":33,"w":136,"h":281},"sourceSize":{"w":150,"h":348}},"theme_stacked_loop_00038.png":{"frame":{"x":422,"y":570,"w":136,"h":280},"rotated":false,"trimmed":true,"spriteSourceSize":{"x":8,"y":33,"w":136,"h":280},"sourceSize":{"w":150,"h":348}}},"meta":{"app":"http://www.codeandweb.com/texturepacker","version":"1.0","image":"atlas-mdpi.png","format":"RGBA8888","size":{"w":1024,"h":1024},"scale":"0.6","smartupdate":"$TexturePacker:SmartUpdate:2fd5d1defded1db81437c6ea9c41ec31:aa3ba86afdc703fe363667668b77e0f5:c14696c3042bf61f22ffb22a391e50cf$"}}