{"frames":{"symbol_blur_theme_1.png":{"frame":{"x":2,"y":2,"w":169,"h":370},"rotated":false,"trimmed":true,"spriteSourceSize":{"x":10,"y":31,"w":169,"h":370},"sourceSize":{"w":188,"h":435}},"symbol_blur_theme_1_01.png":{"frame":{"x":2,"y":729,"w":169,"h":141},"rotated":true,"trimmed":true,"spriteSourceSize":{"x":10,"y":26,"w":169,"h":141},"sourceSize":{"w":188,"h":192}},"symbol_blur_theme_1_02.png":{"frame":{"x":175,"y":113,"w":140,"h":142},"rotated":true,"trimmed":true,"spriteSourceSize":{"x":20,"y":25,"w":140,"h":142},"sourceSize":{"w":188,"h":192}},"symbol_blur_theme_1_03.png":{"frame":{"x":293,"y":420,"w":158,"h":137},"rotated":true,"trimmed":true,"spriteSourceSize":{"x":12,"y":25,"w":158,"h":137},"sourceSize":{"w":188,"h":192}},"symbol_blur_theme_2.png":{"frame":{"x":451,"y":862,"w":123,"h":130},"rotated":false,"trimmed":true,"spriteSourceSize":{"x":20,"y":43,"w":123,"h":130},"sourceSize":{"w":164,"h":215}},"symbol_blur_theme_3.png":{"frame":{"x":382,"y":257,"w":135,"h":141},"rotated":false,"trimmed":true,"spriteSourceSize":{"x":15,"y":25,"w":135,"h":141},"sourceSize":{"w":166,"h":192}},"symbol_blur_theme_4.png":{"frame":{"x":175,"y":583,"w":142,"h":129},"rotated":true,"trimmed":true,"spriteSourceSize":{"x":11,"y":42,"w":142,"h":129},"sourceSize":{"w":164,"h":215}},"symbol_blur_theme_5.png":{"frame":{"x":321,"y":121,"w":132,"h":137},"rotated":true,"trimmed":true,"spriteSourceSize":{"x":16,"y":39,"w":132,"h":137},"sourceSize":{"w":164,"h":215}},"symbol_blur_theme_6.png":{"frame":{"x":175,"y":2,"w":150,"h":107},"rotated":false,"trimmed":true,"spriteSourceSize":{"x":8,"y":43,"w":150,"h":107},"sourceSize":{"w":166,"h":192}},"symbol_blur_theme_7.png":{"frame":{"x":379,"y":726,"w":132,"h":94},"rotated":true,"trimmed":true,"spriteSourceSize":{"x":17,"y":49,"w":132,"h":94},"sourceSize":{"w":166,"h":192}},"symbol_blur_theme_8.png":{"frame":{"x":2,"y":902,"w":120,"h":99},"rotated":true,"trimmed":true,"spriteSourceSize":{"x":23,"y":47,"w":120,"h":99},"sourceSize":{"w":166,"h":192}},"symbol_theme_2.png":{"frame":{"x":503,"y":2,"w":123,"h":109},"rotated":false,"trimmed":true,"spriteSourceSize":{"x":22,"y":5,"w":123,"h":109},"sourceSize":{"w":166,"h":117}},"symbol_theme_3.png":{"frame":{"x":330,"y":874,"w":136,"h":117},"rotated":true,"trimmed":true,"spriteSourceSize":{"x":15,"y":0,"w":136,"h":117},"sourceSize":{"w":166,"h":117}},"symbol_theme_4.png":{"frame":{"x":268,"y":729,"w":141,"h":107},"rotated":true,"trimmed":true,"spriteSourceSize":{"x":13,"y":5,"w":141,"h":107},"sourceSize":{"w":166,"h":117}},"symbol_theme_5.png":{"frame":{"x":462,"y":121,"w":132,"h":116},"rotated":true,"trimmed":true,"spriteSourceSize":{"x":17,"y":1,"w":132,"h":116},"sourceSize":{"w":166,"h":117}},"symbol_theme_6.png":{"frame":{"x":294,"y":257,"w":152,"h":84},"rotated":true,"trimmed":true,"spriteSourceSize":{"x":7,"y":17,"w":152,"h":84},"sourceSize":{"w":166,"h":117}},"symbol_theme_7.png":{"frame":{"x":429,"y":582,"w":132,"h":71},"rotated":true,"trimmed":true,"spriteSourceSize":{"x":17,"y":23,"w":132,"h":71},"sourceSize":{"w":166,"h":117}},"symbol_theme_8.png":{"frame":{"x":105,"y":902,"w":120,"h":77},"rotated":true,"trimmed":true,"spriteSourceSize":{"x":23,"y":20,"w":120,"h":77},"sourceSize":{"w":166,"h":117}},"Theme_1.png":{"frame":{"x":2,"y":376,"w":169,"h":349},"rotated":false,"trimmed":true,"spriteSourceSize":{"x":10,"y":42,"w":169,"h":349},"sourceSize":{"w":188,"h":435}},"theme_1_01.png":{"frame":{"x":147,"y":729,"w":169,"h":117},"rotated":true,"trimmed":true,"spriteSourceSize":{"x":10,"y":0,"w":169,"h":117},"sourceSize":{"w":188,"h":117}},"theme_1_02.png":{"frame":{"x":186,"y":902,"w":140,"h":117},"rotated":false,"trimmed":true,"spriteSourceSize":{"x":20,"y":0,"w":140,"h":117},"sourceSize":{"w":188,"h":117}},"theme_1_03.png":{"frame":{"x":175,"y":420,"w":159,"h":114},"rotated":true,"trimmed":true,"spriteSourceSize":{"x":12,"y":0,"w":159,"h":114},"sourceSize":{"w":188,"h":117}},"theme_1_wild_00059_01.png":{"frame":{"x":330,"y":2,"w":169,"h":115},"rotated":false,"trimmed":true,"spriteSourceSize":{"x":9,"y":2,"w":169,"h":115},"sourceSize":{"w":188,"h":117}},"theme_1_wild_00059_02.png":{"frame":{"x":308,"y":582,"w":140,"h":117},"rotated":true,"trimmed":true,"spriteSourceSize":{"x":19,"y":0,"w":140,"h":117},"sourceSize":{"w":188,"h":117}},"theme_1_wild_00059_03.png":{"frame":{"x":175,"y":257,"w":159,"h":115},"rotated":true,"trimmed":true,"spriteSourceSize":{"x":11,"y":0,"w":159,"h":115},"sourceSize":{"w":188,"h":117}}},"meta":{"app":"http://www.codeandweb.com/texturepacker","version":"1.0","image":"atlas-hdpi.png","format":"RGBA8888","size":{"w":1024,"h":1024},"scale":"0.75","smartupdate":"$TexturePacker:SmartUpdate:4cd1ec1e9e3e8743d370d0d03a099bee:da22a011cd339ca10c091e1a8b77ca0d:c14696c3042bf61f22ffb22a391e50cf$"}}